README.md
setup.py
figure_formating/FormatPlot.py
figure_formating/__init__.py
figure_formating/testing.py
figure_formating.egg-info/PKG-INFO
figure_formating.egg-info/SOURCES.txt
figure_formating.egg-info/dependency_links.txt
figure_formating.egg-info/not-zip-safe
figure_formating.egg-info/top_level.txt