Metadata-Version: 1.0
Name: figure-formating
Version: 0.2
Summary: format the plotted figures
Home-page: UNKNOWN
Author: Zhaoyun Ma
Author-email: mazhaoyunyh@gmail.com
License: UNKNOWN
Platform: UNKNOWN
